py_progress_tracker/__init__.py
py_progress_tracker/measure.py
py_progress_tracker/state.py
py_progress_tracker/track.py
py_progress_tracker-0.7.0.dist-info/WHEEL
py_progress_tracker-0.7.0.dist-info/METADATA
py_progress_tracker-0.7.0.dist-info/RECORD
