Metadata-Version: 2.1
Name: py-progress-tracker
Version: 0.7.0
Summary: A simple benchmarking library
Author: Zama
Author-email: hello@zama.ai
Requires-Python: >=3.7
Classifier: Programming Language :: Python :: 3
Classifier: Programming Language :: Python :: 3.7
Classifier: Programming Language :: Python :: 3.8
Classifier: Programming Language :: Python :: 3.9
Classifier: Programming Language :: Python :: 3.10
Classifier: Programming Language :: Python :: 3.11
Requires-Dist: colorama (>=0.4.4,<0.5.0)
Requires-Dist: psutil (>=5.8.0,<6.0.0)
Requires-Dist: py-cpuinfo (>=8.0.0,<9.0.0)
Requires-Dist: tabulate (>=0.8.9,<0.9.0)
Requires-Dist: termcolor (>=1.1.0,<2.0.0)
